pyncoda/__init__.py
pyncoda/ncoda_00a_projectoverview.md
pyncoda/ncoda_00b_directory_design.py
pyncoda/ncoda_00c_save_output_log.py
pyncoda/ncoda_00d_cleanvarsutils.py
pyncoda/ncoda_00e_geoutilities.py
pyncoda/ncoda_00f_hua_structure.py
pyncoda/ncoda_00g_community_options.py
pyncoda/ncoda_00g_tidy.py
pyncoda/ncoda_00h_bldg_archetype_structure.py
pyncoda/ncoda_02b_cleanblockdata.py
pyncoda/ncoda_02c_cleanbuildingdata.py
pyncoda/ncoda_02d_addresspoint.py
pyncoda/ncoda_04a_Figures.py
pyncoda/ncoda_04b_foliummaps.py
pyncoda/ncoda_04c_poptableresults.py
pyncoda/ncoda_06a_PDF_functions.py
pyncoda/ncoda_06c_Codebook.py
pyncoda/ncoda_06d_INCOREDataService.py
pyncoda/ncoda_07a_generate_hui.py
pyncoda/ncoda_07c_generate_addpt.py
pyncoda/ncoda_07d_run_hua_workflow.py
pyncoda/ncoda_07e_generate_prec.py
pyncoda/ncoda_07f_run_prechui_workflow.py
pyncoda/ncoda_07i_process_communities.py
pyncoda/99_SandboxCode/SandboxAE/__init__.py
pyncoda/99_SandboxCode/SandboxAE/__init__2021-08-17.py
pyncoda/99_SandboxCode/SandboxAE/_lodes_data_structure.py
pyncoda/99_SandboxCode/SandboxAE/lodes_datautil.py
pyncoda/99_SandboxCode/SandboxAE/lodes_fullloop.py
pyncoda/99_SandboxCode/SandboxAE/lodes_mcmcsa_loops.py
pyncoda/99_SandboxCode/SandboxAE/lodes_mcmcsa_util.py
pyncoda/99_SandboxCode/SandboxNPR/prechui_code/Explore.py
pyncoda/99_SandboxCode/SandboxNPR/prechui_code/FitnessChecks.py
pyncoda/99_SandboxCode/SandboxNPR/prechui_code/generate_prechui_community.py
pyncoda/99_SandboxCode/SandboxNPR/prechui_code/hui_add_categorical_char.py
pyncoda/99_SandboxCode/SandboxNPR/prechui_code/merge_hu_prec_worklow.py
pyncoda/99_SandboxCode/SandboxNPR/prechui_code/prechui_worflow.py
pyncoda/99_SandboxCode/SandboxNPR/prechui_code/run_hu_prec_workflow.py
pyncoda/99_SandboxCode/SandboxNPR/prechui_code/tidy_censusapi.py
pyncoda/99_SandboxCode/SandboxNPR/prechui_lodes_code/ICD02c_intersect_prechui_nces.py
pyncoda/99_SandboxCode/SandboxNPR/prechui_lodes_code/ICD02d_intersect_prechui_lodes.py
simcenter_pyncoda_fork-3.0.0.post1.dist-info/licenses/LICENSE
simcenter_pyncoda_fork-3.0.0.post1.dist-info/METADATA
simcenter_pyncoda_fork-3.0.0.post1.dist-info/WHEEL
simcenter_pyncoda_fork-3.0.0.post1.dist-info/top_level.txt
simcenter_pyncoda_fork-3.0.0.post1.dist-info/RECORD
