Metadata-Version: 2.4
Name: simcenter-pyncoda-fork
Version: 3.0.0.post1
Summary: A Python package for generating synthetic household and population data for community resilience analysis
Author: Nathanael Rosenheim
License: Mozilla Public License Version 2.0
Project-URL: Homepage, https://github.com/npr99/intersect-community-data
Classifier: Development Status :: 4 - Beta
Classifier: Intended Audience :: Science/Research
Classifier: License :: OSI Approved :: Mozilla Public License 2.0 (MPL 2.0)
Classifier: Operating System :: OS Independent
Classifier: Programming Language :: Python :: 3
Classifier: Programming Language :: Python :: 3.8
Classifier: Programming Language :: Python :: 3.9
Classifier: Programming Language :: Python :: 3.10
Classifier: Programming Language :: Python :: 3.11
Classifier: Programming Language :: Python :: 3.12
Classifier: Programming Language :: Python :: 3.13
Classifier: Topic :: Scientific/Engineering
Classifier: Topic :: Scientific/Engineering :: GIS
Requires-Python: >=3.8
License-File: LICENSE
Requires-Dist: numpy>=1.26.4
Requires-Dist: pandas>=2.2.2
Requires-Dist: scipy>=1.13.1
Requires-Dist: scikit-learn>=1.4.2
Requires-Dist: geopandas>=0.14.2
Requires-Dist: shapely>=2.0.1
Requires-Dist: fiona>=1.9.5
Requires-Dist: pyproj>=3.6.1
Requires-Dist: rasterio>=1.3.10
Requires-Dist: geopy>=2.4.1
Requires-Dist: geographiclib>=2.0
Requires-Dist: affine>=2.4.0
Requires-Dist: mercantile>=1.2.1
Requires-Dist: snuggs>=1.4.7
Requires-Dist: matplotlib>=3.8.4
Requires-Dist: seaborn>=0.13.2
Requires-Dist: folium>=0.14.0
Requires-Dist: contextily>=1.6.0
Requires-Dist: requests>=2.32.2
Requires-Dist: wget>=3.2
Requires-Dist: fpdf2>=2.7.9
Requires-Dist: ipywidgets>=8.1.2
Requires-Dist: IPython
Requires-Dist: scooby>=0.10.0
Provides-Extra: incore
Requires-Dist: pyincore; extra == "incore"
Provides-Extra: dev
Requires-Dist: pytest; extra == "dev"
Requires-Dist: pytest-cov; extra == "dev"
Requires-Dist: black; extra == "dev"
Requires-Dist: flake8; extra == "dev"
Requires-Dist: jupyter; extra == "dev"
Requires-Dist: notebook; extra == "dev"
Provides-Extra: docs
Requires-Dist: sphinx; extra == "docs"
Requires-Dist: sphinx-rtd-theme; extra == "docs"
Dynamic: license-file
